rwalocation/__init__.py
rwalocation/data.json
rwalocation/main.py
rwalocation-0.1.2.dist-info/LICENSE
rwalocation-0.1.2.dist-info/METADATA
rwalocation-0.1.2.dist-info/WHEEL
rwalocation-0.1.2.dist-info/entry_points.txt
rwalocation-0.1.2.dist-info/top_level.txt
rwalocation-0.1.2.dist-info/RECORD
