Metadata-Version: 2.1
Name: rwalocation
Version: 0.1.2
Summary: A Python library for listing locations in Rwanda
Home-page: https://github.com/Kasulejoseph/Ahantu.git
Author: kasule joseph
Author-email: kasule06joseph@gmail.com
License: License :: OSI Approved :: MIT License
Keywords: Rwanda,Locations,Places,Ahantu,rwalocation
Platform: UNKNOWN
Classifier: Programming Language :: Python
Requires-Python: >=3.6
